hardware_benchmark/__init__.py
hardware_benchmark/main.py
hardware_benchmark/benchmark/__init__.py
hardware_benchmark/benchmark/benchmarks.py
hardware_benchmark/benchmark/monitoring.py
hardware_benchmark/benchmark/rendering.py
hardware_benchmark/core/__init__.py
hardware_benchmark/core/cli.py
hardware_benchmark/core/config.py
hardware_benchmark/core/utils.py
hardware_benchmark/data/__init__.py
hardware_benchmark/data/datasets.py
hardware_benchmark/models/__init__.py
hardware_benchmark/models/models.py
hardware_benchmark/output/__init__.py
hardware_benchmark/output/output.py
hardware_benchmark-0.1.4.dist-info/METADATA
hardware_benchmark-0.1.4.dist-info/WHEEL
hardware_benchmark-0.1.4.dist-info/entry_points.txt
hardware_benchmark-0.1.4.dist-info/top_level.txt
hardware_benchmark-0.1.4.dist-info/RECORD
