Metadata-Version: 2.4
Name: hardware-benchmark
Version: 0.1.4
Summary: A deep learning model hardware benchmarking tool
Home-page: https://github.com/Zihan-D/hardware-bench-yolo
Author: zihan.deng
Author-email: "zihan.deng" <zihan.deng0517@gmail.com>
Project-URL: Repository, https://github.com/Zihan-D/hardware-bench-yolo.git
Keywords: deep learning,machine learning,hardware,benchmark,pytorch,performance,AI,python
Classifier: Development Status :: 4 - Beta
Classifier: Intended Audience :: Developers
Classifier: Intended Audience :: Science/Research
Classifier: Programming Language :: Python :: 3
Classifier: Programming Language :: Python :: 3.8
Classifier: Programming Language :: Python :: 3.9
Classifier: Programming Language :: Python :: 3.10
Classifier: Programming Language :: Python :: 3.11
Requires-Python: >=3.8
Requires-Dist: torch>=1.9.0
Requires-Dist: torchvision>=0.10.0
Requires-Dist: numpy>=1.19.0
Requires-Dist: psutil>=5.8.0
Requires-Dist: Pillow>=8.0.0
Requires-Dist: tqdm>=4.60.0
Requires-Dist: opencv-python
Requires-Dist: timm>=0.6.0
Provides-Extra: full
Requires-Dist: ultralytics>=8.0.0; extra == "full"
Requires-Dist: timm; extra == "full"
Requires-Dist: segmentation-models-pytorch>=0.3.0; extra == "full"
Requires-Dist: nvidia-ml-py3>=7.352.0; extra == "full"
Requires-Dist: matplotlib>=3.3.0; extra == "full"
Requires-Dist: seaborn>=0.11.0; extra == "full"
Provides-Extra: dev
Requires-Dist: pytest>=6.0; extra == "dev"
Requires-Dist: pytest-cov>=2.0; extra == "dev"
Requires-Dist: black>=21.0; extra == "dev"
Requires-Dist: flake8>=3.8; extra == "dev"
Dynamic: author
Dynamic: home-page
Dynamic: requires-python
